gempaterkini/__init__.py
latestearthquake_indonesia_rpelin-0.0.3.dist-info/LICENSE
latestearthquake_indonesia_rpelin-0.0.3.dist-info/METADATA
latestearthquake_indonesia_rpelin-0.0.3.dist-info/WHEEL
latestearthquake_indonesia_rpelin-0.0.3.dist-info/top_level.txt
latestearthquake_indonesia_rpelin-0.0.3.dist-info/RECORD
