Metadata-Version: 2.1
Name: latestearthquake-indonesia-rpelin
Version: 0.0.3
Summary: This package will detect the latest earthquakes from BMKG Indonesia
Author-email: Ruri Pelinandang <ruri.pelinandang@gmail.com>
Project-URL: Homepage, https://github.com/rpelin-creative/latest-indonesian-earthquake
Project-URL: Issues, https://github.com/rpelin-creative/latest-indonesian-earthquake/issues
Classifier: Programming Language :: Python :: 3
Classifier: License :: OSI Approved :: GNU Affero General Public License v3
Classifier: Operating System :: OS Independent
Classifier: Development Status :: 4 - Beta
Requires-Python: >=3.8
License-File: LICENSE
